{"title":"Extreme heat impacting V/Line train services from Saturday 9 March to Tuesday 12 March 2024","date":"2024-03-09","eventImage":null,"articleContent":"<h1>Extreme heat impacting V/Line train services from Saturday 9 March to Tuesday 12 March 2024</h1> <p>Travelling in Victoria &gt; Regional Victoria</p> <p>Hot weather is forecast for parts of Victoria from Saturday 9 March to Tuesday 12 March 2024. Extreme heat timetables will be operating across parts of the V/Line network.</p><p>V/Line will be implementing extreme heat timetables for the following lines:</p><h3>Saturday 9 March</h3><ul><li>Ararat</li><li>Ballarat</li><li>Bendigo</li><li>Echuca</li><li>Geelong</li><li>Maryborough</li><li>Swan Hill</li><li>Warrnambool</li></ul><h3>Sunday 10 March</h3><ul><li>Ararat</li><li>Ballarat</li><li>Bendigo</li><li>Echuca</li><li>Geelong</li><li>Maryborough</li><li>Swan Hill</li><li>Warrnambool</li></ul><h3>Monday 11 March</h3><ul><li>Ararat</li><li>Bairnsdale</li><li>Ballarat</li><li>Bendigo</li><li>Echuca</li><li>Geelong (39°C)</li><li>Maryborough</li><li>Swan Hill</li><li>Traralgon</li><li>Warrnambool (39°C)</li></ul><h3>Tuesday 12 March</h3><p>There will a partial extreme heat timetable implemented for the following lines:</p><ul><li>Bendigo</li><li>Echuca</li><li>Swan Hill</li></ul><p>Passengers are encouraged to check the extreme heat timetable for their individual lines and allow extra time for their journeys. </p><h3>Extreme heat timetables</h3><p>View the extreme heat timetables, and allow extra time for your journey.</p><p>Download the <a href=\"Geelong-Melbourne-(Heat-timetable-39).pdf\">Geelong Line extreme heat timetable</a></p><p>Download the <a href=\"Ballarat-Melbourne-(Heat-timetable-36).pdf\">Ballarat Line extreme heat timetable</a></p><p>Download the <a href=\"Ararat-Melbourne-(Heat-timetable-36).pdf\">Ararat extreme heat timetable</a></p><p>Download the <a href=\"Horsham-Melbourne-(Heat-timetable-36).pdf\">Horsham, Dimboola, Nhill extreme heat timetable</a></p><p>Download the <a href=\"Maryborough-Melbourne-(Heat-timetable-36).pdf\">Maryborough extreme heat timetable</a></p><p>Download the <a href=\"Bendigo-Melbourne-(Heat-timetable-36).pdf\">Bendigo Line extreme heat timetable</a></p><p>Download the <a href=\"Swan-Hill-Melbourne-(Heat-timetable-36).pdf\">Swan Hill extreme heat timetable</a></p><p>Download the <a href=\"Moama-Echuca-Melbourne-(Heat-timetable-36).pdf\">Echuca extreme heat timetable</a></p><p><a href=\"Warrnambool-Melbourne-(Heat-timetable-39).pdf\">Download the Warrnambool extreme heat timetable</a></p>","articleDescription":"Hot weather is forecast for parts of Victoria from Saturday 9 March to Tuesday 12 March 2024. Extreme heat timetables will be operating across parts of the V/Line network.","pdfLinks":["https://www.vline.com.au/getattachment/79d5b4ed-9407-4277-897b-332a9237fce1/Geelong-Melbourne-(Heat-timetable-39)","https://www.vline.com.au/getattachment/d0f7d493-55f8-4115-ac1e-092cf09f4a9a/Ballarat-Melbourne-(Heat-timetable-36)","https://www.vline.com.au/getattachment/02a26163-a769-464b-bdf6-52b6f0683ed3/Ararat-Melbourne-(Heat-timetable-36)","https://www.vline.com.au/getattachment/25a4a163-b16a-488b-9291-67230763a8f3/Horsham-Melbourne-(Heat-timetable-36)","https://www.vline.com.au/getattachment/4f7c8f04-ac83-4a34-89c4-f831dd79369e/Maryborough-Melbourne-(Heat-timetable-36)","https://www.vline.com.au/getattachment/50979d5d-2b0a-4155-bb32-8017552e5794/Bendigo-Melbourne-(Heat-timetable-36)","https://www.vline.com.au/getattachment/97ae6a9c-c090-46b1-b01a-356bf902577e/Swan-Hill-Melbourne-(Heat-timetable-36)","https://www.vline.com.au/getattachment/cb81b48c-7e65-4b88-9ff5-d0f37bc2bd07/Moama-Echuca-Melbourne-(Heat-timetable-36)","https://www.vline.com.au/getattachment/6a971615-e747-418a-80e4-d26403f54ebe/Warrnambool-Melbourne-(Heat-timetable-39)"],"category":["Travelling in Victoria","Regional Victoria"],"imgLinks":[]}